vladk_neural_network/__init__.py
vladk_neural_network/model/__init__.py
vladk_neural_network/model/activation.py
vladk_neural_network/model/base.py
vladk_neural_network/model/layer.py
vladk_neural_network/model/loss.py
vladk_neural_network/model/metric.py
vladk_neural_network/model/optimizer.py
vladk_neural_network-0.1.21.dist-info/LICENSE.md
vladk_neural_network-0.1.21.dist-info/METADATA
vladk_neural_network-0.1.21.dist-info/WHEEL
vladk_neural_network-0.1.21.dist-info/RECORD
