Metadata-Version: 2.1
Name: vladk-neural-network
Version: 0.1.21
Summary: Mini-library that implements a simple version of a feedforward neural network (FNN) and convolutional neural network (CNN) from scratch using Python and PyTorch
Home-page: https://github.com/Vladfsociety/vladk-neural-network
Author: Vlad
Requires-Python: >=3.12,<4.0
Classifier: Programming Language :: Python :: 3
Classifier: Programming Language :: Python :: 3.12
Requires-Dist: tensorflow (>=2.17.0,<3.0.0)
Requires-Dist: torch (>=2.4.0,<3.0.0)
Project-URL: Repository, https://github.com/Vladfsociety/vladk-neural-network
